salt_kafka/__init__.py
salt_kafka/engines/__init__.py
salt_kafka/engines/kafka_consumer.py
salt_kafka/modules/__init__.py
salt_kafka/modules/kafkamod.py
salt_kafka/states/__init__.py
salt_kafka/states/kafkamod.py
salt_kafka-0.2.0.dist-info/licenses/LICENSE
salt_kafka-0.2.0.dist-info/WHEEL
salt_kafka-0.2.0.dist-info/entry_points.txt
salt_kafka-0.2.0.dist-info/METADATA
salt_kafka-0.2.0.dist-info/RECORD
