Metadata-Version: 2.4
Name: salt-kafka
Version: 0.2.0
Summary: Manage Kafka clusters with Salt
Keywords: kafka,salt
License-Expression: MIT
License-File: LICENSE
Classifier: Development Status :: 3 - Alpha
Classifier: Intended Audience :: System Administrators
Classifier: Programming Language :: Python :: 3
Requires-Dist: confluent-kafka>=2.4.0
Requires-Dist: salt>=3006
Requires-Python: >=3.10
Project-URL: source, https://codeberg.org/kfdm/salt-kafka
